{
  "grammar_quiz": [
    {
      "level": "Easy",
      "questions": [
        {
          "id": 1,
          "question": "How many days are in a week?",
          "options": ["5", "6", "7", "8"],
          "correct_answer": "7",
          "grammar_type": "Number, Colour & Days, Months"
        },
        {
          "id": 2,
          "question": "What colour is a banana?",
          "options": ["Red", "Blue", "Yellow", "Green"],
          "correct_answer": "Yellow",
          "grammar_type": "Number, Colour & Days, Months"
        },
        {
          "id": 3,
          "question": "Which number comes after nine?",
          "options": ["Eight", "Ten", "Seven", "Eleven"],
          "correct_answer": "Ten",
          "grammar_type": "Number, Colour & Days, Months"
        },
        {
          "id": 4,
          "question": "What day comes after Monday?",
          "options": ["Sunday", "Wednesday", "Tuesday", "Friday"],
          "correct_answer": "Tuesday",
          "grammar_type": "Number, Colour & Days, Months"
        },
        {
          "id": 5,
          "question": "How many months are in a year?",
          "options": ["10", "11", "12", "13"],
          "correct_answer": "12",
          "grammar_type": "Number, Colour & Days, Months"
        },
        {
          "id": 6,
          "question": "What colour is the sky on a clear day?",
          "options": ["Green", "Black", "White", "Blue"],
          "correct_answer": "Blue",
          "grammar_type": "Number, Colour & Days, Months"
        },
        {
          "id": 7,
          "question": "What is the first month of the year?",
          "options": ["February", "March", "December", "January"],
          "correct_answer": "January",
          "grammar_type": "Number, Colour & Days, Months"
        },
        {
          "id": 8,
          "question": "What is the number '3' in words?",
          "options": ["Two", "Three", "Four", "Five"],
          "correct_answer": "Three",
          "grammar_type": "Number, Colour & Days, Months"
        },
        {
          "id": 9,
          "question": "What day is the weekend?",
          "options": ["Monday", "Wednesday", "Saturday", "Tuesday"],
          "correct_answer": "Saturday",
          "grammar_type": "Number, Colour & Days, Months"
        },
        {
          "id": 10,
          "question": "What colour are most leaves on a tree?",
          "options": ["Yellow", "Brown", "Green", "Red"],
          "correct_answer": "Green",
          "grammar_type": "Number, Colour & Days, Months"
        },
        {
          "id": 11,
          "question": "Which number comes before five?",
          "options": ["Six", "Three", "Four", "Seven"],
          "correct_answer": "Four",
          "grammar_type": "Number, Colour & Days, Months"
        },
        {
          "id": 12,
          "question": "What is the last day of the week?",
          "options": ["Monday", "Friday", "Saturday", "Sunday"],
          "correct_answer": "Sunday",
          "grammar_type": "Number, Colour & Days, Months"
        },
        {
          "id": 13,
          "question": "What colour is a stop sign?",
          "options": ["Green", "Yellow", "Red", "Blue"],
          "correct_answer": "Red",
          "grammar_type": "Number, Colour & Days, Months"
        },
        {
          "id": 14,
          "question": "How many sides does a triangle have?",
          "options": ["2", "3", "4", "5"],
          "correct_answer": "3",
          "grammar_type": "Number, Colour & Days, Months"
        },
        {
          "id": 15,
          "question": "Which month comes after June?",
          "options": ["May", "July", "August", "September"],
          "correct_answer": "July",
          "grammar_type": "Number, Colour & Days, Months"
        },
        {
          "id": 16,
          "question": "What is the colour of snow?",
          "options": ["Black", "Grey", "White", "Blue"],
          "correct_answer": "White",
          "grammar_type": "Number, Colour & Days, Months"
        },
        {
          "id": 17,
          "question": "What is the number '1' in words?",
          "options": ["One", "Two", "Ten", "On"],
          "correct_answer": "One",
          "grammar_type": "Number, Colour & Days, Months"
        },
        {
          "id": 18,
          "question": "What day comes before Friday?",
          "options": ["Saturday", "Thursday", "Wednesday", "Tuesday"],
          "correct_answer": "Thursday",
          "grammar_type": "Number, Colour & Days, Months"
        },
        {
          "id": 19,
          "question": "In which month is Christmas celebrated?",
          "options": ["November", "January", "October", "December"],
          "correct_answer": "December",
          "grammar_type": "Number, Colour & Days, Months"
        },
        {
          "id": 20,
          "question": "What colour is coal?",
          "options": ["White", "Black", "Brown", "Grey"],
          "correct_answer": "Black",
          "grammar_type": "Number, Colour & Days, Months"
        },
        {
          "id": 21,
          "question": "How many fingers are on one hand?",
          "options": ["4", "5", "6", "10"],
          "correct_answer": "5",
          "grammar_type": "Number, Colour & Days, Months"
        },
        {
          "id": 22,
          "question": "What is the first day of the school week?",
          "options": ["Sunday", "Saturday", "Monday", "Tuesday"],
          "correct_answer": "Monday",
          "grammar_type": "Number, Colour & Days, Months"
        },
        {
          "id": 23,
          "question": "What colour is a carrot?",
          "options": ["Purple", "Orange", "White", "Green"],
          "correct_answer": "Orange",
          "grammar_type": "Number, Colour & Days, Months"
        },
        {
          "id": 24,
          "question": "What is the number '6' in words?",
          "options": ["Seven", "Six", "Five", "Sex"],
          "correct_answer": "Six",
          "grammar_type": "Number, Colour & Days, Months"
        },
        {
          "id": 25,
          "question": "Which month comes before April?",
          "options": ["May", "June", "March", "February"],
          "correct_answer": "March",
          "grammar_type": "Number, Colour & Days, Months"
        },
        {
          "id": 26,
          "question": "How many wheels does a bicycle have?",
          "options": ["1", "2", "3", "4"],
          "correct_answer": "2",
          "grammar_type": "Number, Colour & Days, Months"
        },
        {
          "id": 27,
          "question": "What day is between Tuesday and Thursday?",
          "options": ["Monday", "Friday", "Wednesday", "Sunday"],
          "correct_answer": "Wednesday",
          "grammar_type": "Number, Colour & Days, Months"
        },
        {
          "id": 28,
          "question": "What colour is the sun?",
          "options": ["Blue", "Green", "White", "Yellow"],
          "correct_answer": "Yellow",
          "grammar_type": "Number, Colour & Days, Months"
        },
        {
          "id": 29,
          "question": "How many legs does a spider have?",
          "options": ["6", "8", "10", "4"],
          "correct_answer": "8",
          "grammar_type": "Number, Colour & Days, Months"
        },
        {
          "id": 30,
          "question": "What is the last month of the year?",
          "options": ["January", "November", "December", "October"],
          "correct_answer": "December",
          "grammar_type": "Number, Colour & Days, Months"
        },
        {
          "id": 31,
          "question": "What colour do you get when you mix red and white?",
          "options": ["Orange", "Pink", "Purple", "Grey"],
          "correct_answer": "Pink",
          "grammar_type": "Number, Colour & Days, Months"
        },
        {
          "id": 32,
          "question": "What is the number '11' in words?",
          "options": ["Ten", "Twelve", "Eleven", "Twenty"],
          "correct_answer": "Eleven",
          "grammar_type": "Number, Colour & Days, Months"
        },
        {
          "id": 33,
          "question": "What do we call the day after today?",
          "options": ["Yesterday", "Tomorrow", "Today", "Now"],
          "correct_answer": "Tomorrow",
          "grammar_type": "Number, Colour & Days, Months"
        },
        {
          "id": 34,
          "question": "How many colours are in a rainbow?",
          "options": ["5", "6", "7", "8"],
          "correct_answer": "7",
          "grammar_type": "Number, Colour & Days, Months"
        },
        {
          "id": 35,
          "question": "Which month has the shortest name?",
          "options": ["June", "July", "May", "April"],
          "correct_answer": "May",
          "grammar_type": "Number, Colour & Days, Months"
        },
        {
          "id": 36,
          "question": "What is the number that comes after 19?",
          "options": ["18", "20", "21", "17"],
          "correct_answer": "20",
          "grammar_type": "Number, Colour & Days, Months"
        },
        {
          "id": 37,
          "question": "What colour is chocolate?",
          "options": ["Black", "White", "Brown", "Red"],
          "correct_answer": "Brown",
          "grammar_type": "Number, Colour & Days, Months"
        },
        {
          "id": 38,
          "question": "What day of the week is a holiday in many countries?",
          "options": ["Monday", "Wednesday", "Friday", "Sunday"],
          "correct_answer": "Sunday",
          "grammar_type": "Number, Colour & Days, Months"
        },
        {
          "id": 39,
          "question": "How many seasons are there in a year?",
          "options": ["2", "3", "4", "5"],
          "correct_answer": "4",
          "grammar_type": "Number, Colour & Days, Months"
        },
        {
          "id": 40,
          "question": "In which month do we celebrate Independence Day in India?",
          "options": ["January", "August", "October", "November"],
          "correct_answer": "August",
          "grammar_type": "Number, Colour & Days, Months"
        },
        {
          "id": 41,
          "question": "What colour is the opposite of white?",
          "options": ["Blue", "Red", "Black", "Green"],
          "correct_answer": "Black",
          "grammar_type": "Number, Colour & Days, Months"
        },
        {
          "id": 42,
          "question": "What is the number '15' in words?",
          "options": ["Fifty", "Five-teen", "Fifteen", "Fiveteen"],
          "correct_answer": "Fifteen",
          "grammar_type": "Number, Colour & Days, Months"
        },
        {
          "id": 43,
          "question": "What do we call the day before today?",
          "options": ["Tomorrow", "Today", "Yesterday", "Then"],
          "correct_answer": "Yesterday",
          "grammar_type": "Number, Colour & Days, Months"
        },
        {
          "id": 44,
          "question": "What is the colour of a crow?",
          "options": ["White", "Black", "Grey", "Brown"],
          "correct_answer": "Black",
          "grammar_type": "Number, Colour & Days, Months"
        },
        {
          "id": 45,
          "question": "How many sides does a square have?",
          "options": ["3", "4", "5", "6"],
          "correct_answer": "4",
          "grammar_type": "Number, Colour & Days, Months"
        },
        {
          "id": 46,
          "question": "Which month comes between September and November?",
          "options": ["August", "December", "October", "July"],
          "correct_answer": "October",
          "grammar_type": "Number, Colour & Days, Months"
        },
        {
          "id": 47,
          "question": "What is the colour of milk?",
          "options": ["Yellow", "White", "Cream", "Blue"],
          "correct_answer": "White",
          "grammar_type": "Number, Colour & Days, Months"
        },
        {
          "id": 48,
          "question": "What is the number '2' in words?",
          "options": ["To", "Too", "Two", "Twice"],
          "correct_answer": "Two",
          "grammar_type": "Number, Colour & Days, Months"
        },
        {
          "id": 49,
          "question": "Which is a school day?",
          "options": ["Saturday", "Sunday", "Holiday", "Friday"],
          "correct_answer": "Friday",
          "grammar_type": "Number, Colour & Days, Months"
        },
        {
          "id": 50,
          "question": "What is the colour of a brinjal (eggplant)?",
          "options": ["Green", "Red", "Yellow", "Purple"],
          "correct_answer": "Purple",
          "grammar_type": "Number, Colour & Days, Months"
        },
        {
          "id": 51,
          "question": "How many hours are in a day?",
          "options": ["12", "24", "30", "60"],
          "correct_answer": "24",
          "grammar_type": "Number, Colour & Days, Months"
        },
        {
          "id": 52,
          "question": "What is the day after Saturday?",
          "options": ["Monday", "Friday", "Sunday", "Tuesday"],
          "correct_answer": "Sunday",
          "grammar_type": "Number, Colour & Days, Months"
        },
        {
          "id": 53,
          "question": "What is the colour of a ladybug?",
          "options": ["Red and Black", "Yellow and Black", "Green and White", "Blue and Red"],
          "correct_answer": "Red and Black",
          "grammar_type": "Number, Colour & Days, Months"
        },
        {
          "id": 54,
          "question": "What is the month before January?",
          "options": ["February", "November", "December", "March"],
          "correct_answer": "December",
          "grammar_type": "Number, Colour & Days, Months"
        },
        {
          "id": 55,
          "question": "What is the number '7' in words?",
          "options": ["Six", "Eight", "Seven", "Eleven"],
          "correct_answer": "Seven",
          "grammar_type": "Number, Colour & Days, Months"
        },
        {
          "id": 56,
          "question": "What colour are grapes sometimes?",
          "options": ["Blue", "Orange", "Pink", "Green"],
          "correct_answer": "Green",
          "grammar_type": "Number, Colour & Days, Months"
        },
        {
          "id": 57,
          "question": "How many years are in a decade?",
          "options": ["5", "10", "50", "100"],
          "correct_answer": "10",
          "grammar_type": "Number, Colour & Days, Months"
        },
        {
          "id": 58,
          "question": "What day comes two days after Monday?",
          "options": ["Tuesday", "Wednesday", "Thursday", "Friday"],
          "correct_answer": "Wednesday",
          "grammar_type": "Number, Colour & Days, Months"
        },
        {
          "id": 59,
          "question": "What month is associated with spring season?",
          "options": ["December", "October", "March", "January"],
          "correct_answer": "March",
          "grammar_type": "Number, Colour & Days, Months"
        },
        {
          "id": 60,
          "question": "What is the colour of a sunflower?",
          "options": ["Red", "Orange", "Yellow", "White"],
          "correct_answer": "Yellow",
          "grammar_type": "Number, Colour & Days, Months"
        }
      ]
    },
    {
      "level": "Medium",
      "questions": [
        {
          "id": 61,
          "question": "What two colours make purple?",
          "options": ["Red and Yellow", "Yellow and Blue", "Blue and Red", "Black and White"],
          "correct_answer": "Blue and Red",
          "grammar_type": "Number, Colour & Days, Months"
        },
        {
          "id": 62,
          "question": "What is the third day of the week?",
          "options": ["Monday", "Tuesday", "Wednesday", "Thursday"],
          "correct_answer": "Wednesday",
          "grammar_type": "Number, Colour & Days, Months"
        },
        {
          "id": 63,
          "question": "Which is the correct spelling for the number 8?",
          "options": ["Eigt", "Aight", "Eight", "Eit"],
          "correct_answer": "Eight",
          "grammar_type": "Number, Colour & Days, Months"
        },
        {
          "id": 64,
          "question": "How many days are in the month of February in a normal year?",
          "options": ["28", "29", "30", "31"],
          "correct_answer": "28",
          "grammar_type": "Number, Colour & Days, Months"
        },
        {
          "id": 65,
          "question": "Which colour is NOT a primary colour?",
          "options": ["Red", "Yellow", "Blue", "Green"],
          "correct_answer": "Green",
          "grammar_type": "Number, Colour & Days, Months"
        },
        {
          "id": 66,
          "question": "What is the eighth month of the year?",
          "options": ["July", "August", "September", "October"],
          "correct_answer": "August",
          "grammar_type": "Number, Colour & Days, Months"
        },
        {
          "id": 67,
          "question": "What number is 'twenty-five'?",
          "options": ["24", "25", "35", "26"],
          "correct_answer": "25",
          "grammar_type": "Number, Colour & Days, Months"
        },
        {
          "id": 68,
          "question": "If today is Friday, what day was yesterday?",
          "options": ["Saturday", "Thursday", "Wednesday", "Sunday"],
          "correct_answer": "Thursday",
          "grammar_type": "Number, Colour & Days, Months"
        },
        {
          "id": 69,
          "question": "What is a lighter shade of blue called?",
          "options": ["Navy blue", "Dark blue", "Sky blue", "Royal blue"],
          "correct_answer": "Sky blue",
          "grammar_type": "Number, Colour & Days, Months"
        },
        {
          "id": 70,
          "question": "How many days are in March?",
          "options": ["28", "29", "30", "31"],
          "correct_answer": "31",
          "grammar_type": "Number, Colour & Days, Months"
        },
        {
          "id": 71,
          "question": "What is the ordinal number for '2nd'?",
          "options": ["Two", "Second", "Twice", "Twoth"],
          "correct_answer": "Second",
          "grammar_type": "Number, Colour & Days, Months"
        },
        {
          "id": 72,
          "question": "Which is the correct spelling for the colour of grass?",
          "options": ["Grean", "Grene", "Green", "Grin"],
          "correct_answer": "Green",
          "grammar_type": "Number, Colour & Days, Months"
        },
        {
          "id": 73,
          "question": "What two colours make orange?",
          "options": ["Red and Blue", "Blue and Yellow", "Yellow and Red", "Green and Red"],
          "correct_answer": "Yellow and Red",
          "grammar_type": "Number, Colour & Days, Months"
        },
        {
          "id": 74,
          "question": "Which of these months has 30 days?",
          "options": ["January", "May", "July", "April"],
          "correct_answer": "April",
          "grammar_type": "Number, Colour & Days, Months"
        },
        {
          "id": 75,
          "question": "What is the number 'fifty'?",
          "options": ["15", "50", "55", "5"],
          "correct_answer": "50",
          "grammar_type": "Number, Colour & Days, Months"
        },
        {
          "id": 76,
          "question": "What is the colour of a ruby gemstone?",
          "options": ["Blue", "Green", "Red", "Yellow"],
          "correct_answer": "Red",
          "grammar_type": "Number, Colour & Days, Months"
        },
        {
          "id": 77,
          "question": "If yesterday was Sunday, what day is tomorrow?",
          "options": ["Saturday", "Monday", "Tuesday", "Wednesday"],
          "correct_answer": "Tuesday",
          "grammar_type": "Number, Colour & Days, Months"
        },
        {
          "id": 78,
          "question": "What is the tenth month of the year?",
          "options": ["September", "October", "November", "December"],
          "correct_answer": "October",
          "grammar_type": "Number, Colour & Days, Months"
        },
        {
          "id": 79,
          "question": "Which is the correct spelling for the day after Monday?",
          "options": ["Tuseday", "Teusday", "Tuesday", "Twosday"],
          "correct_answer": "Tuesday",
          "grammar_type": "Number, Colour & Days, Months"
        },
        {
          "id": 80,
          "question": "The colour 'violet' is a shade of ____.",
          "options": ["Red", "Blue", "Purple", "Pink"],
          "correct_answer": "Purple",
          "grammar_type": "Number, Colour & Days, Months"
        },
        {
          "id": 81,
          "question": "How many weeks are there approximately in a month?",
          "options": ["2", "3", "4", "5"],
          "correct_answer": "4",
          "grammar_type": "Number, Colour & Days, Months"
        },
        {
          "id": 82,
          "question": "What comes after 'third'?",
          "options": ["Second", "Fifth", "Fourth", "First"],
          "correct_answer": "Fourth",
          "grammar_type": "Number, Colour & Days, Months"
        },
        {
          "id": 83,
          "question": "Which is the correct spelling for the month between July and September?",
          "options": ["Agust", "Augest", "August", "Augast"],
          "correct_answer": "August",
          "grammar_type": "Number, Colour & Days, Months"
        },
        {
          "id": 84,
          "question": "What is the colour of an emerald gemstone?",
          "options": ["Red", "Blue", "Green", "Yellow"],
          "correct_answer": "Green",
          "grammar_type": "Number, Colour & Days, Months"
        },
        {
          "id": 85,
          "question": "How many days are in a year?",
          "options": ["360", "365", "370", "356"],
          "correct_answer": "365",
          "grammar_type": "Number, Colour & Days, Months"
        },
        {
          "id": 86,
          "question": "What day of the week does 'Wed' stand for?",
          "options": ["Weekend", "Wednesday", "Weekday", "Welcome day"],
          "correct_answer": "Wednesday",
          "grammar_type": "Number, Colour & Days, Months"
        },
        {
          "id": 87,
          "question": "What is the colour 'maroon' a shade of?",
          "options": ["Brown", "Red", "Orange", "Purple"],
          "correct_answer": "Red",
          "grammar_type": "Number, Colour & Days, Months"
        },
        {
          "id": 88,
          "question": "Which number is 'one hundred'?",
          "options": ["10", "100", "1000", "1"],
          "correct_answer": "100",
          "grammar_type": "Number, Colour & Days, Months"
        },
        {
          "id": 89,
          "question": "Which month is the shortest?",
          "options": ["April", "June", "September", "February"],
          "correct_answer": "February",
          "grammar_type": "Number, Colour & Days, Months"
        },
        {
          "id": 90,
          "question": "The day before Sunday is ____.",
          "options": ["Monday", "Friday", "Saturday", "Tuesday"],
          "correct_answer": "Saturday",
          "grammar_type": "Number, Colour & Days, Months"
        },
        {
          "id": 91,
          "question": "What two colours make green?",
          "options": ["Red and Yellow", "Blue and Red", "Yellow and Blue", "Black and Yellow"],
          "correct_answer": "Yellow and Blue",
          "grammar_type": "Number, Colour & Days, Months"
        },
        {
          "id": 92,
          "question": "Which number is a dozen?",
          "options": ["10", "12", "20", "24"],
          "correct_answer": "12",
          "grammar_type": "Number, Colour & Days, Months"
        },
        {
          "id": 93,
          "question": "Which season is associated with the month of December in the Northern Hemisphere?",
          "options": ["Spring", "Summer", "Autumn", "Winter"],
          "correct_answer": "Winter",
          "grammar_type": "Number, Colour & Days, Months"
        },
        {
          "id": 94,
          "question": "What is the sixth day of the week?",
          "options": ["Thursday", "Friday", "Saturday", "Sunday"],
          "correct_answer": "Saturday",
          "grammar_type": "Number, Colour & Days, Months"
        },
        {
          "id": 95,
          "question": "Which is the correct spelling for the number 40?",
          "options": ["Fourty", "Fourtye", "Forty", "Forte"],
          "correct_answer": "Forty",
          "grammar_type": "Number, Colour & Days, Months"
        },
        {
          "id": 96,
          "question": "The colour 'grey' is a mix of which two colours?",
          "options": ["Black and White", "Blue and White", "Black and Blue", "Green and White"],
          "correct_answer": "Black and White",
          "grammar_type": "Number, Colour & Days, Months"
        },
        {
          "id": 97,
          "question": "How many days are there in total in July and August?",
          "options": ["60", "61", "62", "59"],
          "correct_answer": "62",
          "grammar_type": "Number, Colour & Days, Months"
        },
        {
          "id": 98,
          "question": "What is the day that comes two days before Saturday?",
          "options": ["Sunday", "Wednesday", "Thursday", "Friday"],
          "correct_answer": "Thursday",
          "grammar_type": "Number, Colour & Days, Months"
        },
        {
          "id": 99,
          "question": "The colour 'indigo' is found in a ____.",
          "options": ["Traffic light", "Rainbow", "Flower", "Fruit"],
          "correct_answer": "Rainbow",
          "grammar_type": "Number, Colour & Days, Months"
        },
        {
          "id": 100,
          "question": "Which is the only month that can have less than 30 days?",
          "options": ["April", "June", "September", "February"],
          "correct_answer": "February",
          "grammar_type": "Number, Colour & Days, Months"
        },
        {
          "id": 101,
          "question": "What is the ordinal number for '5th'?",
          "options": ["Five", "Fiveth", "Fifth", "Fift"],
          "correct_answer": "Fifth",
          "grammar_type": "Number, Colour & Days, Months"
        },
        {
          "id": 102,
          "question": "The colour 'silver' is a shiny shade of ____.",
          "options": ["White", "Grey", "Yellow", "Blue"],
          "correct_answer": "Grey",
          "grammar_type": "Number, Colour & Days, Months"
        },
        {
          "id": 103,
          "question": "If the first of the month is a Monday, what day is the fourth?",
          "options": ["Tuesday", "Wednesday", "Thursday", "Friday"],
          "correct_answer": "Thursday",
          "grammar_type": "Number, Colour & Days, Months"
        },
        {
          "id": 104,
          "question": "What number is half of 50?",
          "options": ["20", "25", "30", "35"],
          "correct_answer": "25",
          "grammar_type": "Number, Colour & Days, Months"
        },
        {
          "id": 105,
          "question": "Which month is named after a Roman god of war?",
          "options": ["May", "June", "July", "March"],
          "correct_answer": "March",
          "grammar_type": "Number, Colour & Days, Months"
        },
        {
          "id": 106,
          "question": "The colour 'amber' is a shade of ____.",
          "options": ["Yellow-Orange", "Blue-Green", "Red-Purple", "Brown-Black"],
          "correct_answer": "Yellow-Orange",
          "grammar_type": "Number, Colour & Days, Months"
        },
        {
          "id": 107,
          "question": "What is the second month of the year?",
          "options": ["January", "February", "March", "April"],
          "correct_answer": "February",
          "grammar_type": "Number, Colour & Days, Months"
        },
        {
          "id": 108,
          "question": "What number is a 'score'?",
          "options": ["10", "12", "20", "50"],
          "correct_answer": "20",
          "grammar_type": "Number, Colour & Days, Months"
        },
        {
          "id": 109,
          "question": "If your birthday is in two days and today is Tuesday, which day is your birthday?",
          "options": ["Wednesday", "Thursday", "Friday", "Saturday"],
          "correct_answer": "Thursday",
          "grammar_type": "Number, Colour & Days, Months"
        },
        {
          "id": 110,
          "question": "The colour 'turquoise' is a blend of blue and ____.",
          "options": ["Red", "Yellow", "Green", "White"],
          "correct_answer": "Green",
          "grammar_type": "Number, Colour & Days, Months"
        }
      ]
    },
    {
      "level": "Hard",
      "questions": [
        {
          "id": 111,
          "question": "How many days are in a leap year?",
          "options": ["364", "365", "366", "367"],
          "correct_answer": "366",
          "grammar_type": "Number, Colour & Days, Months"
        },
        {
          "id": 112,
          "question": "The colour 'teal' is a mixture of blue and ____.",
          "options": ["Yellow", "White", "Black", "Green"],
          "correct_answer": "Green",
          "grammar_type": "Number, Colour & Days, Months"
        },
        {
          "id": 113,
          "question": "What is the Roman numeral for 10?",
          "options": ["I", "V", "X", "L"],
          "correct_answer": "X",
          "grammar_type": "Number, Colour & Days, Months"
        },
        {
          "id": 114,
          "question": "If today is Wednesday, what day will it be in 15 days?",
          "options": ["Wednesday", "Thursday", "Friday", "Saturday"],
          "correct_answer": "Thursday",
          "grammar_type": "Number, Colour & Days, Months"
        },
        {
          "id": 115,
          "question": "Which month gets an extra day during a leap year?",
          "options": ["January", "February", "March", "December"],
          "correct_answer": "February",
          "grammar_type": "Number, Colour & Days, Months"
        },
        {
          "id": 116,
          "question": "Which colour is often associated with royalty?",
          "options": ["Red", "Gold", "Purple", "Blue"],
          "correct_answer": "Purple",
          "grammar_type": "Number, Colour & Days, Months"
        },
        {
          "id": 117,
          "question": "What is the term for a period of two weeks?",
          "options": ["Decade", "Fortnight", "Month", "Score"],
          "correct_answer": "Fortnight",
          "grammar_type": "Number, Colour & Days, Months"
        },
        {
          "id": 118,
          "question": "The colour 'magenta' is a purplish-____.",
          "options": ["Blue", "Red", "Pink", "Orange"],
          "correct_answer": "Red",
          "grammar_type": "Number, Colour & Days, Months"
        },
        {
          "id": 119,
          "question": "How many years are in a century?",
          "options": ["10", "50", "100", "1000"],
          "correct_answer": "100",
          "grammar_type": "Number, Colour & Days, Months"
        },
        {
          "id": 120,
          "question": "If the last day of a 31-day month is a Friday, what day was the first?",
          "options": ["Tuesday", "Wednesday", "Thursday", "Friday"],
          "correct_answer": "Wednesday",
          "grammar_type": "Number, Colour & Days, Months"
        },
        {
          "id": 121,
          "question": "What is the Roman numeral for 5?",
          "options": ["I", "V", "X", "L"],
          "correct_answer": "V",
          "grammar_type": "Number, Colour & Days, Months"
        },
        {
          "id": 122,
          "question": "The colour 'vermilion' is a brilliant shade of ____.",
          "options": ["Green", "Blue", "Red", "Yellow"],
          "correct_answer": "Red",
          "grammar_type": "Number, Colour & Days, Months"
        },
        {
          "id": 123,
          "question": "Which day of the week is named after the Norse god Thor?",
          "options": ["Tuesday", "Wednesday", "Thursday", "Friday"],
          "correct_answer": "Thursday",
          "grammar_type": "Number, Colour & Days, Months"
        },
        {
          "id": 124,
          "question": "What number is 'one thousand, two hundred and thirty-four'?",
          "options": ["1234", "1324", "1432", "1243"],
          "correct_answer": "1234",
          "grammar_type": "Number, Colour & Days, Months"
        },
        {
          "id": 125,
          "question": "A leap year occurs every ____ years.",
          "options": ["2", "3", "4", "5"],
          "correct_answer": "4",
          "grammar_type": "Number, Colour & Days, Months"
        },
        {
          "id": 126,
          "question": "What colour is associated with envy or jealousy in idioms?",
          "options": ["Red", "Green", "Yellow", "Blue"],
          "correct_answer": "Green",
          "grammar_type": "Number, Colour & Days, Months"
        },
        {
          "id": 127,
          "question": "What is the Roman numeral for 6?",
          "options": ["IV", "VI", "IIIIII", "VX"],
          "correct_answer": "VI",
          "grammar_type": "Number, Colour & Days, Months"
        },
        {
          "id": 128,
          "question": "What day was it three days before Tuesday?",
          "options": ["Saturday", "Sunday", "Monday", "Friday"],
          "correct_answer": "Saturday",
          "grammar_type": "Number, Colour & Days, Months"
        },
        {
          "id": 129,
          "question": "The colour 'chartreuse' is a mix of yellow and ____.",
          "options": ["Blue", "Red", "Green", "Orange"],
          "correct_answer": "Green",
          "grammar_type": "Number, Colour & Days, Months"
        },
        {
          "id": 130,
          "question": "How many months have exactly 30 days?",
          "options": ["3", "4", "5", "6"],
          "correct_answer": "4",
          "grammar_type": "Number, Colour & Days, Months"
        },
        {
          "id": 131,
          "question": "What is the number 'ninety-nine'?",
          "options": ["90", "19", "99", "909"],
          "correct_answer": "99",
          "grammar_type": "Number, Colour & Days, Months"
        },
        {
          "id": 132,
          "question": "What is the first day of a new year?",
          "options": ["December 31st", "January 1st", "December 1st", "January 31st"],
          "correct_answer": "January 1st",
          "grammar_type": "Number, Colour & Days, Months"
        },
        {
          "id": 133,
          "question": "The colour 'sepia' is a shade of ____.",
          "options": ["Reddish-brown", "Greenish-blue", "Yellowish-pink", "Dark grey"],
          "correct_answer": "Reddish-brown",
          "grammar_type": "Number, Colour & Days, Months"
        },
        {
          "id": 134,
          "question": "How many years are in a millennium?",
          "options": ["10", "100", "1000", "10000"],
          "correct_answer": "1000",
          "grammar_type": "Number, Colour & Days, Months"
        },
        {
          "id": 135,
          "question": "If a meeting is on the third Tuesday of a month, and the 1st was a Sunday, what is the date?",
          "options": ["15th", "16th", "17th", "18th"],
          "correct_answer": "17th",
          "grammar_type": "Number, Colour & Days, Months"
        },
        {
          "id": 136,
          "question": "What is the Roman numeral for 4?",
          "options": ["IIII", "IV", "VI", "IIV"],
          "correct_answer": "IV",
          "grammar_type": "Number, Colour & Days, Months"
        },
        {
          "id": 137,
          "question": "What colour is the gemstone sapphire typically?",
          "options": ["Red", "Green", "Yellow", "Blue"],
          "correct_answer": "Blue",
          "grammar_type": "Number, Colour & Days, Months"
        },
        {
          "id": 138,
          "question": "A quarter of a year is how many months?",
          "options": ["2", "3", "4", "6"],
          "correct_answer": "3",
          "grammar_type": "Number, Colour & Days, Months"
        },
        {
          "id": 139,
          "question": "What is the number for half a dozen?",
          "options": ["5", "6", "8", "12"],
          "correct_answer": "6",
          "grammar_type": "Number, Colour & Days, Months"
        },
        {
          "id": 140,
          "question": "The colour 'crimson' is a deep shade of ____.",
          "options": ["Blue", "Green", "Red", "Purple"],
          "correct_answer": "Red",
          "grammar_type": "Number, Colour & Days, Months"
        },
        {
          "id": 141,
          "question": "If it is October, what month was it three months ago?",
          "options": ["June", "July", "August", "September"],
          "correct_answer": "July",
          "grammar_type": "Number, Colour & Days, Months"
        },
        {
          "id": 142,
          "question": "Which of these is a tertiary colour?",
          "options": ["Green", "Orange", "Purple", "Amber"],
          "correct_answer": "Amber",
          "grammar_type": "Number, Colour & Days, Months"
        },
        {
          "id": 143,
          "question": "What is 'a score' plus 'a dozen'?",
          "options": ["22", "30", "32", "40"],
          "correct_answer": "32",
          "grammar_type": "Number, Colour & Days, Months"
        },
        {
          "id": 144,
          "question": "Which month is named after the Roman emperor Augustus?",
          "options": ["June", "July", "August", "September"],
          "correct_answer": "August",
          "grammar_type": "Number, Colour & Days, Months"
        },
        {
          "id": 145,
          "question": "What is the Roman numeral for 9?",
          "options": ["VIIII", "IX", "XI", "IVV"],
          "correct_answer": "IX",
          "grammar_type": "Number, Colour & Days, Months"
        },
        {
          "id": 146,
          "question": "To be 'in the red' idiomatically means to be...",
          "options": ["happy", "angry", "in debt", "successful"],
          "correct_answer": "in debt",
          "grammar_type": "Number, Colour & Days, Months"
        },
        {
          "id": 147,
          "question": "The period from January to June is the first ____ of the year.",
          "options": ["Quarter", "Half", "Term", "Semester"],
          "correct_answer": "Half",
          "grammar_type": "Number, Colour & Days, Months"
        },
        {
          "id": 148,
          "question": "What is the number for 'three-quarters' of 100?",
          "options": ["25", "50", "75", "80"],
          "correct_answer": "75",
          "grammar_type": "Number, Colour & Days, Months"
        },
        {
          "id": 149,
          "question": "The colour 'ochre' is a shade of ____.",
          "options": ["Greenish-blue", "Purplish-red", "Yellowish-brown", "Greyish-white"],
          "correct_answer": "Yellowish-brown",
          "grammar_type": "Number, Colour & Days, Months"
        },
        {
          "id": 150,
          "question": "If today is the 10th of May, what will the date be in a fortnight?",
          "options": ["20th of May", "24th of May", "27th of May", "30th of May"],
          "correct_answer": "24th of May",
          "grammar_type": "Number, Colour & Days, Months"
        }
      ]
    }
  ]
}

